{
  "tree": [
    {
      "code": "C-2",
      "label": "商品品質",
      "level": 1,
      "domain": "product_quality",
      "children": [
        {
          "code": "C-2-1",
          "label": "網路品質",
          "level": 2,
          "children": [
            {
              "code": "C-2-1-1",
              "allow": [
                "特定室內/地下室/停車場完全沒訊號",
                "市區內訊號差、走出室內才恢復",
                "訊號忽有忽無、需借熱點才能用",
                "特定場館現場網頁打不開、差點無法進場"
              ],
              "canon": "旅客移動中於建築內/地下室/停車場/場館/郊區等特定地點收不到訊號、需走出去才有、或訊號時好時壞；核心是「地點相關、時好時壞」",
              "label": "訊號微弱",
              "level": 3,
              "forbid": [
                "整趟從頭到尾連不上、需重開機才解決 → 歸 C-2-1-3",
                "宣稱可用地區/涵蓋範圍與實際不符 → 歸 C-1",
                "純嫌網速慢但收得到訊號 → 歸 C-2-1-2"
              ],
              "negative_cases": [
                "『整趟行程從頭到尾都連不上網，重開機好幾次都沒用』看似訊號微弱，實為完全斷線 → 歸 C-2-1-3",
                "『網速慢到地圖都跑不出來，訊號是有但很慢』看似訊號微弱，實為網速緩慢 → 歸 C-2-1-2"
              ],
              "positive_cases": [
                "飯店房間裡完全收不到訊號，要走到大廳才有一點點",
                "在地下停車場完全沒訊號，訊號時好時壞，只好開熱點分享",
                "進到展館裡網頁一直讀不出來，差點無法刷票進場"
              ]
            },
            {
              "code": "C-2-1-2",
              "allow": [
                "能連上但看網頁/傳照片影片明顯卡慢",
                "只有 4G 速度、到不了 5G",
                "行動支付時通時卡、有時跑不動"
              ],
              "canon": "收得到訊號、能連上網，但查地圖、傳照片影片、行動支付等操作明顯變慢或卡頓，或只有 4G 到不了 5G；核心是「有連線但慢」",
              "label": "網速緩慢",
              "level": 3,
              "forbid": [
                "完全沒訊號、根本連不上 → 歸 C-2-1-1 或 C-2-1-3",
                "流量用完被降速但方案本就寫明流量上限 → 屬正常使用限制，非品質負向",
                "隱藏限速但頁面沒寫 → 歸 C-1"
              ],
              "negative_cases": [
                "『某天開始完全沒有網路，訊號顯示有格但打不開任何網頁』看似網速緩慢，實為完全斷線 → 歸 C-2-1-3",
                "『用超過方案流量後被降速，但商品頁本來就寫明流量上限』看似網速緩慢，實為正常使用限制，非品質負向"
              ],
              "positive_cases": [
                "有訊號但傳照片傳超久，等到心累",
                "只有 4G，怎麼樣都跑不到 5G，網頁載入很慢",
                "要用行動支付時網路卡卡的，付款差點失敗"
              ]
            },
            {
              "code": "C-2-1-3",
              "allow": [
                "完全不能用，只好另外付費買其他 eSIM",
                "訊號整個消失，重啟/飛航開關都沒用，需緊急重開機才恢復",
                "用到某天開始斷連、顯示有連線卻無網際網路",
                "同批多張卡中有一張怎麼設都無法上網、只好重買"
              ],
              "canon": "整段或某一天完全連不上網、突然斷訊需重開機才恢復、須另購他卡補救，或同批多張卡中有一張整支報廢需重買；核心是「完全不能用、需重開機/換卡才解決」",
              "label": "完全斷線",
              "level": 3,
              "forbid": [
                "只是某地點沒訊號、其他地方正常 → 歸 C-2-1-1",
                "只是速度慢但仍連得上 → 歸 C-2-1-2"
              ],
              "negative_cases": [
                "『只有在某個景點收不到訊號，其他地方都正常』看似完全斷線，實為訊號微弱 → 歸 C-2-1-1",
                "『網路是有點慢，但至少還連得上』看似完全斷線，實為網速緩慢 → 歸 C-2-1-2"
              ],
              "positive_cases": [
                "用到第三天突然完全斷線，飛航模式開關都沒用，只好重開機才恢復",
                "整支 eSIM 直接報廢，怎麼設定都上不了網，只好另外買一張",
                "顯示有訊號格數，但實際上完全沒有網路可用"
              ]
            }
          ],
          "canon": "抱怨網路訊號弱/慢/斷等實體不佳(含eSIM)，非啟用操作卡關→C-4-1",
          "forbid": [
            "整趟連不上網被誤認成兌換/開通卡關，實為訊號/網路本身故障 → 歸 C-2-1，非 C-4-1"
          ],
          "negative_cases": [
            "eSIM 全程連不上/條碼失效但屬網路斷線 → 歸 C-2-1-3，非 C-4-1"
          ]
        },
        {
          "code": "C-2-2",
          "label": "餐飲品質",
          "level": 2,
          "children": [
            {
              "code": "C-2-2-1",
              "allow": [
                "餐點難吃、味道差、食材不新鮮",
                "菜色過鹹過淡、熱食只有微溫",
                "菜式種類/可選項目少",
                "熱盤冷盤或醬料補貨跟不上、未見補充"
              ],
              "canon": "餐點難吃、味道差（過鹹過淡、微溫）、食材不新鮮，或菜式種類/可選項目太少、補貨跟不上；核心是「吃到嘴裡好不好吃/夠不夠選」",
              "label": "口味不佳",
              "level": 3,
              "forbid": [
                "份量遠低於宣稱、貨不對板 → 歸 C-1",
                "只抱怨座位擁擠或現場衛生差、未提食物 → 歸 C-2-2-2",
                "頁面已寫明供餐/早餐、僅吃到現場覺得普通難吃 → 仍歸口味不佳，非商品內容"
              ],
              "negative_cases": [
                "『訂的是海鮮大餐結果只有幾隻小蝦，跟介紹完全不成比例』看似口味不佳，實為貨不對板 → 歸 C-1",
                "『用餐區座位擠到手肘都會碰到隔壁桌，但東西還算好吃』看似口味不佳，實為環境/衛生 → 歸 C-2-2-2",
                "餐飲頁面有寫、只是吃起來普通難吃 → 歸 C-2-2-1，非 C-1"
              ],
              "positive_cases": [
                "今天的午餐超難吃，肉質乾柴，味道也怪怪的",
                "主餐都是冷的，只有湯是溫的，吃起來很不開胃",
                "菜色選擇很少，來回就那幾道，很快就吃膩了"
              ]
            },
            {
              "code": "C-2-2-2",
              "allow": [
                "座位擁擠狹小、位置很逼",
                "餐點上有蒼蠅、現場衛生差",
                "用餐環境不舒適、氛圍差"
              ],
              "canon": "用餐時座位擁擠狹小、環境不舒適，或現場衛生差（如餐點有蒼蠅）；核心是「用餐空間/現場衛生」",
              "label": "環境/衛生",
              "level": 3,
              "forbid": [
                "只抱怨食物味道或選擇、沒提環境/衛生 → 歸 C-2-2-1",
                "現場公共衛生設施（如廁所）非用餐本身、由供應商維護 → 歸 C-3-5"
              ],
              "negative_cases": [
                "『菜的味道普普，鹹到有點吃不下』看似環境/衛生，實為口味不佳 → 歸 C-2-2-1",
                "『用餐區旁邊的公用廁所很髒亂』看似環境/衛生，實為場館衛生設施非用餐本身 → 歸 C-3-5"
              ],
              "positive_cases": [
                "用餐區座位擠成一團，根本沒有個人空間",
                "桌上飛來飛去都是蒼蠅，看了食慾全失",
                "餐廳環境油膩又悶熱，坐著很不舒服"
              ]
            }
          ],
          "canon": "抱怨餐飲難吃/不衛生/選項少，非該給沒給→C-3-4、非不合口味→C-6-1"
        },
        {
          "code": "C-2-3",
          "allow": [
            "付 SUV 等級的錢現場卻派一般轎車",
            "訂購車型等級與現場實際到場車輛不符",
            "車輛/設備本身有明顯故障或狀態不佳"
          ],
          "canon": "付了較高等級車型的錢（如 SUV）現場卻派較低等級車輛，或車輛/設備本身狀態不佳、有明顯故障；核心是「有明確付費升等/約定，供應商現場沒依約派對應車型/設備」",
          "label": "車輛設備",
          "level": 2,
          "forbid": [
            "商品頁沒寫清楚車型 → 歸 C-1；頁面有寫但消費者自己預設會錯意 → 歸 C-6-1",
            "車到場型號也對、只是司機開車習慣不好 → 歸駕駛行為相關類目",
            "與駕駛行為類（開車習慣/態度）互斥",
            "車輛安全配備缺損（安全帶等）→ 歸 C-3-5（本類為車型/等級/一般狀態）"
          ],
          "negative_cases": [
            "『商品頁根本沒寫清楚車型是什麼，是我自己以為會有大車』看似車輛設備，實為資訊不符 → 歸 C-1",
            "『車子型號沒錯，但司機開車很魯莽、態度又差』看似車輛設備，實為駕駛行為問題 → 歸 C-3-2-1"
          ],
          "positive_cases": [
            "明明付的是 SUV 等級的錢，現場來的卻是一般小轎車",
            "訂的車型跟到場的完全不一樣，感覺被降規格",
            "車子外觀看起來很舊，坐進去還有異音，感覺隨時會拋錨"
          ]
        },
        {
          "code": "C-2-4",
          "label": "票券兌換",
          "level": 2,
          "children": [
            {
              "code": "C-2-4-1",
              "allow": [
                "方案寫有附券、現場人員沒給，客服事後堅稱已發放",
                "應得的票券/贈品現場沒拿到、申訴後對方否認"
              ],
              "canon": "方案內載明應提供的票券/憑證，現場工作人員沒給，且事後對方堅稱已發放、各說各話；核心是「方案明確有這項、執行面漏發」",
              "label": "票券漏發",
              "level": 3,
              "forbid": [
                "抱怨方案本身沒說清楚有沒有附券 → 歸 C-1",
                "拿到的票券使用範圍/折扣不如預期 → 歸 C-2-4-2"
              ],
              "negative_cases": [
                "『網頁上根本沒寫清楚到底有沒有附贈票券，害我白期待』看似票券漏發，實為資訊不明 → 歸 C-1",
                "『票券是有拿到啦，但能用的地方少得可憐』看似票券漏發，實為價值不符 → 歸 C-2-4-2"
              ],
              "positive_cases": [
                "方案寫明有附贈門票，現場工作人員卻說沒有這回事",
                "應該要拿到的紀念品現場完全沒給，客服還說已經發放過了",
                "憑證明明有包含在方案內，到現場才發現根本沒人給我"
              ]
            },
            {
              "code": "C-2-4-2",
              "allow": [
                "兌換品項數量/金額很小、換算價值很低",
                "並非每間店都能用、需額外查找可用店家",
                "門票全額無折扣時套票能省的很有限"
              ],
              "canon": "以套票折抵餐飲/商品時，實際能兌換的品項數量/金額很有限（如只能換一球、全額票無折扣省不了多少），或使用店家/範圍受限需額外查找；核心是「有給、但兌換價值/使用範圍不划算」",
              "label": "價值不符",
              "level": 3,
              "forbid": [
                "該有的票券現場完全沒發 → 歸 C-2-4-1",
                "票券本身能正常核銷/掃碼、僅嫌換到的價值/範圍不划算 → 歸本類；核銷/掃碼本身失敗 → 歸 C-4-2"
              ],
              "negative_cases": [
                "『說好附的贈品現場直接說沒有，怎麼問都不給』看似價值不符，實為票券漏發 → 歸 C-2-4-1"
              ],
              "positive_cases": [
                "這套票只能換一球冰淇淋，換算下來根本不划算",
                "說是能折抵餐飲，結果只有少數幾間店能用，還要自己找半天",
                "全額票本來就沒有優惠了，套票根本省不到什麼錢"
              ]
            }
          ],
          "canon": "抱怨票券兌到的價值/內容不符實付，非掃不過→C-4-2"
        },
        {
          "code": "C-2-5",
          "allow": [
            "房間髒亂、有異味或蟲",
            "冷氣/熱水/Wi-Fi 等設備故障",
            "隔音差、吵到無法休息",
            "備品不足或清潔不徹底"
          ],
          "canon": "住宿房間本身實體品質差——髒亂、有異味/蟲、設備故障（冷氣/熱水/Wi-Fi 壞）、隔音差、備品或清潔不到位；核心是「住宿實體品質不佳」",
          "label": "住宿品質",
          "level": 2,
          "forbid": [
            "頁面寫四星實際二星、房型與描述不符 → 歸 C-1",
            "臨時被換房或超訂沒房可住 → 歸 C-3",
            "抱怨櫃檯/接待人員態度差 → 歸 C-3-1-1"
          ],
          "negative_cases": [
            "『網頁寫四星飯店，實際入住感覺頂多二星等級，落差很大』看似住宿品質，實為房型與描述不符 → 歸 C-1",
            "『check-in 時被通知客滿沒房，臨時被換到別間旅館』看似住宿品質，實為訂房/超訂問題 → 歸 C-3"
          ],
          "positive_cases": [
            "房間裡有蟲又有一股霉味，完全無法安心入住",
            "冷氣壞掉整晚吹不涼，熱水也忽冷忽熱",
            "隔音超差，隔壁講話跟走廊腳步聲都聽得一清二楚"
          ]
        },
        {
          "code": "C-2-6",
          "allow": [
            "浮潛/滑雪等租借器材老舊、故障或不潔",
            "遊樂/展館設施損壞或維護差",
            "場地髒亂破舊影響使用"
          ],
          "canon": "參加活動或使用場館時，現場器材/遊具/場地設施本身狀態不佳——老舊/故障/不潔、遊樂或展館設施損壞、場地維護不良；核心是「活動/場館的實體設備品質」",
          "label": "設施設備",
          "level": 2,
          "forbid": [
            "交通車輛本身狀態不佳 → 歸 C-2-3",
            "頁面宣稱的設施現場根本沒有 → 歸 C-1",
            "設施因天候臨時停用 → 歸 C-6-4-1",
            "因現場人員沒開放/操作失當 → 歸 C-3",
            "設施本身運作正常、只是覺得不好玩/沒亮點/動物少 → 歸 C-6，非本類"
          ],
          "negative_cases": [
            "『接駁車看起來很老舊，坐起來也不太穩』看似設施設備，實為車輛設備 → 歸 C-2-3",
            "『網頁介紹的兒童遊戲區，現場根本沒有這個設施』看似設施設備，實為資訊不符 → 歸 C-1",
            "設施正常只是覺得沒亮點/不好玩 → 歸 C-6，非 C-2-6"
          ],
          "positive_cases": [
            "浮潛借的裝備又舊又髒，面鏡還有裂痕",
            "遊樂設施看起來很久沒維護，坐上去搖搖晃晃很可怕",
            "展館現場設施破舊髒亂，體驗感很差"
          ]
        }
      ],
      "canon": "評論抱怨產品/服務『實體品質本身』差(網路/餐飲/車輛/住宿/設施/票券價值)。非頁面沒描述(→C-1)、非該給沒給(→C-3-4)、非主觀不合口味或景觀/亮點不如預期(→C-6-1)。",
      "positive_cases": [
        "抱怨網路訊號差/連線不穩定，非設定操作問題本身",
        "抱怨餐點難吃/份量少/食材差，屬實際餐飲品質",
        "抱怨車輛老舊/座椅不適/設施骯髒等實體品質",
        "抱怨兌換到手的票券/商品本身品質差（非兌換操作卡關）",
        "抱怨住宿設施故障、隔音差等實體體驗品質"
      ],
      "negative_cases": [
        "eSIM/門票無法連線啟用或核銷失敗（操作/系統問題）→歸兌換使用，非商品品質",
        "頁面完全沒寫清楚會提供什麼等級的餐飲/設施→歸商品內容，非商品品質",
        "供應商承諾包含某項目卻沒提供（該給沒給）→歸供應商履約，非商品品質",
        "行程步調太趕/沒看到景點，屬安排節奏問題→歸供應商履約，非商品品質",
        "單純覺得餐點不合個人口味、非品質瑕疵→歸客人理解，非商品品質"
      ],
      "forbid": [
        "連線/核銷失敗等操作面問題禁止歸商品品質（應歸兌換使用）"
      ]
    }
  ],
  "_meta": {
    "about": "商品服務品質（評論導向收斂，AI 起草待人審）（判準精煉：8 欄併 4，正反例通用化併入 allow/forbid）",
    "label": "商品服務品質",
    "domain": "product_quality",
    "version": "1.0",
    "l3_total": 10,
    "domain_count": 1,
    "recommended_action": "penalize_breach",
    "thick_fields_status": "ai_refined_pending_review"
  },
  "$schema": "./rule.schema.json"
}
